osblc_lib
