Metadata-Version: 1.0
Name: osblc
Version: 0.1.6
Summary: On s'en bat les couilles !
Home-page: https://gitlab.com/nmartignoni/osblc
Author: Noel Martignoni
Author-email: noel@martignoni.fr
License: UNKNOWN
Platform: UNKNOWN
